filediffs/__init__.py
filediffs/filediffs_cython/__init__.py
filediffs/filediffs_cython/filediffs_cy.cp35-win_amd64.pyd
filediffs/filediffs_cython/filediffs_cy.cpp
filediffs/filediffs_python/__init__.py
filediffs/filediffs_python/filediffs.py
filediffs-0.1.12.data/scripts/filediffs
filediffs-0.1.12.dist-info/LICENSE
filediffs-0.1.12.dist-info/METADATA
filediffs-0.1.12.dist-info/WHEEL
filediffs-0.1.12.dist-info/top_level.txt
filediffs-0.1.12.dist-info/RECORD
