Metadata-Version: 2.1
Name: filediffs
Version: 0.1.12
Summary: Separate two files into three files, each containing lines observed in both files/first file only/second file only. Programmed using Cython.
Home-page: https://github.com/INWTlab/filediffs
Author: Sebastian Cattes
Author-email: sebastian.cattes@inwt-statistics.de
License: MIT
Platform: UNKNOWN
Classifier: Development Status :: 4 - Beta
Classifier: Intended Audience :: Developers
Classifier: Natural Language :: English
Classifier: License :: OSI Approved :: MIT License
Classifier: Programming Language :: Python
Classifier: Programming Language :: Python :: 3
Classifier: Programming Language :: Python :: 3.8
Classifier: Programming Language :: Python :: 3.8
Classifier: Programming Language :: Python :: 3.8
Classifier: Programming Language :: Python :: 3.8
Requires: cython
